orange_story_navigator-0.0.1-py3.9-nspkg.pth
orange_story_navigator-0.0.1.data/data/help/orange3-story-navigator/.buildinfo
orange_story_navigator-0.0.1.data/data/help/orange3-story-navigator/genindex.html
orange_story_navigator-0.0.1.data/data/help/orange3-story-navigator/index.html
orange_story_navigator-0.0.1.data/data/help/orange3-story-navigator/objects.inv
orange_story_navigator-0.0.1.data/data/help/orange3-story-navigator/search.html
orange_story_navigator-0.0.1.data/data/help/orange3-story-navigator/searchindex.js
orange_story_navigator-0.0.1.data/data/help/orange3-story-navigator/_images/dsgdepparser-example.png
orange_story_navigator-0.0.1.data/data/help/orange3-story-navigator/_images/dsgruleset-example.png
orange_story_navigator-0.0.1.data/data/help/orange3-story-navigator/_images/dsgsrl-example.png
orange_story_navigator-0.0.1.data/data/help/orange3-story-navigator/_images/dsgtagger-example2.png
orange_story_navigator-0.0.1.data/data/help/orange3-story-navigator/_sources/index.rst.txt
orange_story_navigator-0.0.1.data/data/help/orange3-story-navigator/_sources/widgets/dsgdepparser.md.txt
orange_story_navigator-0.0.1.data/data/help/orange3-story-navigator/_sources/widgets/dsgruleset.md.txt
orange_story_navigator-0.0.1.data/data/help/orange3-story-navigator/_sources/widgets/dsgsrl.md.txt
orange_story_navigator-0.0.1.data/data/help/orange3-story-navigator/_sources/widgets/dsgtagger.md.txt
orange_story_navigator-0.0.1.data/data/help/orange3-story-navigator/_static/_sphinx_javascript_frameworks_compat.js
orange_story_navigator-0.0.1.data/data/help/orange3-story-navigator/_static/basic.css
orange_story_navigator-0.0.1.data/data/help/orange3-story-navigator/_static/custom.css
orange_story_navigator-0.0.1.data/data/help/orange3-story-navigator/_static/doctools.js
orange_story_navigator-0.0.1.data/data/help/orange3-story-navigator/_static/documentation_options.js
orange_story_navigator-0.0.1.data/data/help/orange3-story-navigator/_static/file.png
orange_story_navigator-0.0.1.dist-info/LICENSE
orange_story_navigator-0.0.1.dist-info/METADATA
orange_story_navigator-0.0.1.dist-info/WHEEL
orange_story_navigator-0.0.1.dist-info/entry_points.txt
orange_story_navigator-0.0.1.dist-info/namespace_packages.txt
orange_story_navigator-0.0.1.dist-info/top_level.txt
orange_story_navigator-0.0.1.dist-info/RECORD
