Metadata-Version: 2.1
Name: orange-story-navigator
Version: 0.0.1
Summary: Narrative analysis add-on for the Orange 3 data mining software package.
Home-page: https://github.com/navigating-stories/orange-story-navigator
Author: Kody Moodley, The Netherlands eScience Center
Author-email: k.moodley@esciencecenter.nl
License: GPLv3
Keywords: story analysis,narrative theory,natural language processing,story networks,character networks,data mining,machine learning,artificial intelligence,orange,orange3 add-on
Platform: UNKNOWN
Classifier: Development Status :: 4 - Beta
Classifier: Environment :: X11 Applications :: Qt
Classifier: Environment :: Console
Classifier: Environment :: Plugins
Classifier: Programming Language :: Python
Classifier: License :: OSI Approved :: GNU General Public License v3 or later (GPLv3+)
Classifier: Operating System :: OS Independent
Classifier: Topic :: Scientific/Engineering :: Artificial Intelligence
Classifier: Topic :: Scientific/Engineering :: Visualization
Classifier: Topic :: Software Development :: Libraries :: Python Modules
Classifier: Intended Audience :: Education
Classifier: Intended Audience :: Science/Research
Classifier: Intended Audience :: Developers
License-File: LICENSE
Requires-Dist: anyqt
Requires-Dist: Orange3 (>=3.32)
Requires-Dist: Orange3-text (>=1.7)
Requires-Dist: orange-widget-base
Requires-Dist: scikit-learn
Provides-Extra: gui
Requires-Dist: AnyQt ; extra == 'gui'
Provides-Extra: doc
Requires-Dist: sphinx ; extra == 'doc'
Requires-Dist: recommonmark ; extra == 'doc'
Requires-Dist: sphinx-rtd-theme ; extra == 'doc'
Provides-Extra: rest
Requires-Dist: numpydoc ; extra == 'rest'
Provides-Extra: test
Requires-Dist: coverage ; extra == 'test'
